<?xml version="1.0" encoding="utf-8"?>
<IncrementalBankBuild Version="6" Flags="878078161">
	<Platform GUID="{15055DC0-08EA-4543-A775-699656B8EF57}">
		<Banks>
			<Language ID="393239870">
				<File Name="Ambience" Hash="1978453144" Timestamp="131511372881422440"/>
				<File Name="Effects" Hash="2161120610" Timestamp="131541627861252220"/>
				<File Name="Footsteps" Hash="3727015415" Timestamp="131511344146036584"/>
				<File Name="Init" Hash="898061812" Timestamp="131541581926284132"/>
				<File Name="VOs" Hash="1353446029" Timestamp="131541659219651016"/>
			</Language>
		</Banks>
		<XMLInfo>
			<Language ID="-1">
				<File Name="" Hash="503606062" Timestamp="131541659219791392"/>
			</Language>
		</XMLInfo>
	</Platform>
	<Platform GUID="{BD52FE50-EBCC-4FBC-A0A5-46622CC30E21}">
		<Banks>
			<Language ID="393239870">
				<File Name="Ambience" Hash="1978453144" Timestamp="131511372883748636"/>
				<File Name="Effects" Hash="2161120610" Timestamp="131541627869193847"/>
				<File Name="Footsteps" Hash="3727015415" Timestamp="131511344247306172"/>
				<File Name="Init" Hash="3808212186" Timestamp="131541581932470429"/>
				<File Name="VOs" Hash="1353446029" Timestamp="131541659222750610"/>
			</Language>
		</Banks>
		<XMLInfo>
			<Language ID="-1">
				<File Name="" Hash="856940484" Timestamp="131541659222871134"/>
			</Language>
		</XMLInfo>
	</Platform>
</IncrementalBankBuild>
